project/FormulaGenerator.py
project/__init__.py
project/main.py
project/main2.py
project/package/__init__.py
project/package/parseFormula.py
project/package/parseTree.py
project/package/propParser.py
project/package/parse/__init__.py
project/package/parse/parser.py
formula_generator-0.1.0.dist-info/METADATA
formula_generator-0.1.0.dist-info/WHEEL
formula_generator-0.1.0.dist-info/top_level.txt
formula_generator-0.1.0.dist-info/RECORD
