Metadata-Version: 2.1
Name: formula-generator
Version: 0.1.0
Summary: My first Python library
Home-page: https://formula-generator.readthedocs.io/
Author: Dania
License: MIT
Platform: UNKNOWN
Requires-Dist: click
Requires-Dist: pythonds
Requires-Dist: z3
